SlurmDagman/__init__.py
SlurmDagman/constants.py
SlurmDagman/config/__init__.py
SlurmDagman/config/manager.py
SlurmDagman/config/data/__init__.py
SlurmDagman/config/data/package.py
SlurmDagman/config/data/process.py
SlurmDagman/config/defaults/__init__.py
SlurmDagman/config/defaults/common.py
SlurmDagman/config/defaults/package.py
SlurmDagman/config/defaults/process.py
SlurmDagman/config/utils/__init__.py
SlurmDagman/config/utils/converters.py
SlurmDagman/config/utils/package.py
SlurmDagman/dag/__init__.py
SlurmDagman/dag/utils/__init__.py
SlurmDagman/dag/utils/rescue_dag.py
SlurmDagman/process/__init__.py
SlurmDagman/process/worker.py
SlurmDagman/process/command/__init__.py
SlurmDagman/process/command/arguments.py
SlurmDagman/translators/__init__.py
SlurmDagman/translators/condor_to_slurm.py
SlurmDagman/utils/__init__.py
SlurmDagman/utils/process.py
SlurmDagman-0.1.7.data/data/etc/SlurmDagman/SlurmDagman.conf
SlurmDagman-0.1.7.data/scripts/condor_dag_to_slurm_dag
SlurmDagman-0.1.7.data/scripts/fix_dag_file
SlurmDagman-0.1.7.data/scripts/slurm_cancel_dag
SlurmDagman-0.1.7.data/scripts/slurm_dagman
SlurmDagman-0.1.7.data/scripts/slurm_submit_dag
SlurmDagman-0.1.7.dist-info/LICENSE
SlurmDagman-0.1.7.dist-info/METADATA
SlurmDagman-0.1.7.dist-info/WHEEL
SlurmDagman-0.1.7.dist-info/top_level.txt
SlurmDagman-0.1.7.dist-info/RECORD
