Metadata-Version: 2.1
Name: SlurmDagman
Version: 0.1.7
Summary: Application to run a DAG with SLURM.
Home-page: https://github.com/AndresTanasijczuk/SlurmDagman
Author: Andres Tanasijczuk (Université catholique de Louvain)
Author-email: cp3-support@listes.uclouvain.be
License: GPL-3.0-or-later
Keywords: slurm,dag
Platform: UNKNOWN
Classifier: Development Status :: 5 - Production/Stable
Classifier: Intended Audience :: Developers
Classifier: Intended Audience :: Science/Research
Classifier: Topic :: Scientific/Engineering
Classifier: Topic :: Scientific/Engineering :: Information Analysis
Classifier: Topic :: Scientific/Engineering :: Physics
Classifier: Topic :: Software Development :: Libraries :: Python Modules
Classifier: Topic :: System :: Distributed Computing
Classifier: License :: OSI Approved :: GNU General Public License v3 (GPLv3)
Classifier: Operating System :: OS Independent
Classifier: Programming Language :: Python :: 2
Classifier: Programming Language :: Python :: 2.7
Classifier: Programming Language :: Python :: 3
Classifier: Programming Language :: Python :: 3.6
Classifier: Programming Language :: Python :: 3.7
License-File: LICENSE
